mcp_server_vefaas_function/__init__.py
mcp_server_vefaas_function/sign.py
mcp_server_vefaas_function/sse.py
mcp_server_vefaas_function/stdio.py
mcp_server_vefaas_function/vefaas_server.py
mcp_server_vefaas_function/vefaas_server_test.py
vefaas_function_mcp_server-0.1.0.dist-info/METADATA
vefaas_function_mcp_server-0.1.0.dist-info/WHEEL
vefaas_function_mcp_server-0.1.0.dist-info/entry_points.txt
vefaas_function_mcp_server-0.1.0.dist-info/top_level.txt
vefaas_function_mcp_server-0.1.0.dist-info/RECORD
