Metadata-Version: 2.4
Name: vefaas-function-mcp-server
Version: 0.1.0
Summary: MCP server for managing veFaaS (Volc Engine Function as a Service) functions
Requires-Python: >=3.13
Requires-Dist: mcp==1.3.0
Requires-Dist: volcengine-python-sdk==1.1.3
Requires-Dist: requests==2.32.3
